[
	{
		"jobName": "技术总监",
		"pay": "50-100K",
		"address": "深圳 宝安区 福永",
		"year": "5-10年",
		"education": "本科",
		"companyName": "跨越速运",
		"tmt": "物流/仓储",
		"financing": "A轮",
		"peopleNum": "10000人以上",
		"img": "https://img2.bosszhipin.com/mcs/useravatar/20150401/9efebd3de653f939b85afa36b872f9428bee7c70fa2377c34db570f82ca84ea5_s.jpg",
		"recruiter": "柯小姐",
		"type": "招聘者"
	},
	{
		"jobName": "sensor驱动工程师",
		"pay": "20-40K",
		"address": "深圳 福田区 梅林",
		"year": "3-5年",
		"education": "本科",
		"companyName": "VIVO",
		"tmt": "移动互联网",
		"financing": "不需要融资",
		"peopleNum": "10000人以上",
		"img": "https://img.bosszhipin.com/boss/avatar/avatar_13.png",
		"recruiter": "周先生",
		"type": "招聘者"
	},
	{
		"jobName": "29912-前端开发工程师",
		"pay": "20-40K",
		"address": "深圳 南山区 科技园",
		"year": "3-5年",
		"education": "本科",
		"companyName": "腾讯",
		"tmt": "互联网",
		"financing": "已上市",
		"peopleNum": "10000人以上",
		"img": "https://img.bosszhipin.com/beijin/mcs/useravatar/20171225/2caae747d6fcc3c7d6e453394371a601889ae7e8d50c9fe480d60ea141065384_s.jpg",
		"recruiter": "coe集团招聘部",
		"type": "招聘者"
	},
	{
		"jobName": "微信支付高级推荐算法",
		"pay": "30-60K",
		"address": "深圳 南山区 科技园",
		"year": "3-5年",
		"education": "本科",
		"companyName": "腾讯",
		"tmt": "互联网",
		"financing": "已上市",
		"peopleNum": "10000人以上",
		"img": "https://img.bosszhipin.com/beijin/mcs/useravatar/20171225/2caae747d6fcc3c7d6e453394371a601889ae7e8d50c9fe480d60ea141065384_s.jpg",
		"recruiter": "coe集团招聘部",
		"type": "招聘者"
	},
	{
		"jobName": "腾讯视频推荐算法",
		"pay": "50-100K",
		"address": "深圳 宝安区 福永",
		"year": "5-10年",
		"education": "本科",
		"companyName": "跨越速运",
		"tmt": "物流/仓储",
		"financing": "A轮",
		"peopleNum": "10000人以上",
		"img": "https://img2.bosszhipin.com/mcs/useravatar/20150401/9efebd3de653f939b85afa36b872f9428bee7c70fa2377c34db570f82ca84ea5_s.jpg",
		"recruiter": "柯小姐",
		"type": "招聘者"
	},
	{
		"jobName": "游戏AI高级算法工程师",
		"pay": "29-58K",
		"address": "深圳 南山区 科技园",
		"year": "3-5年",
		"education": "硕士",
		"companyName": "腾讯",
		"tmt": "互联网",
		"financing": "已上市",
		"peopleNum": "10000人以上",
		"img": "https://img.bosszhipin.com/beijin/mcs/useravatar/20171225/2caae747d6fcc3c7d6e453394371a601889ae7e8d50c9fe480d60ea141065384_s.jpg",
		"recruiter": "coe集团招聘部",
		"type": "招聘者"
	},
	{
		"jobName": "SAP MM 模块实施顾问",
		"pay": "20-25K",
		"address": "上海",
		"year": "3-5年",
		"education": "本科",
		"companyName": "晶科能源",
		"tmt": "新能源",
		"financing": "已上市",
		"peopleNum": "10000人以上",
		"img": "https://img.bosszhipin.com/beijin/mcs/useravatar/20190212/2eca4d7663d464f45c8d86949d92cb7674453c37e868780a5292a974a5b9dbb5_s.jpg",
		"recruiter": "李女士",
		"type": "招聘经理"
	},
	{
		"jobName": "技术支持专家（金融云）",
		"pay": "30-55K",
		"address": "上海",
		"year": "5-10年",
		"education": "本科",
		"companyName": "蚂蚁金服",
		"tmt": "互联网",
		"financing": "C轮",
		"peopleNum": "10000人以上",
		"img": "https://img.bosszhipin.com/beijin/mcs/useravatar/20180929/e60eecd98d2a5dd733cd72f2fd6539ba098e3c80168ddacf4e222832e4b22779_s.jpg",
		"recruiter": "程先生",
		"type": "招聘者"
	},
	{
		"jobName": "杭州-java开发工程师/java技术专家",
		"pay": "25-50K·15薪",
		"address": "天津",
		"year": "3-5年",
		"education": "本科",
		"companyName": "alibaba",
		"tmt": "电子商务",
		"financing": "已上市",
		"peopleNum": "10000人以上",
		"img": "https://img.bosszhipin.com/beijin/mcs/useravatar/20180327/28a18b629df1acfcab14a1b205e3bb77cfcd208495d565ef66e7dff9f98764da_s.jpg",
		"recruiter": "叶先生",
		"type": "招聘者"
	},
	{
		"jobName": "Java架构师",
		"pay": "20-40K",
		"address": "上海",
		"year": "5-10年",
		"education": "本科",
		"companyName": "复星集团总部",
		"tmt": "互联网",
		"financing": "已上市",
		"peopleNum": "10000人以上",
		"img": "https://img.bosszhipin.com/beijin/mcs/useravatar/20190523/37222789daf1124108a1d4e8dbbc9e4e6ceb06809ea5e12b4e33320fd4e1bc32_s.jpg",
		"recruiter": "hrbp",
		"type": "招聘者"
	},
	{
		"jobName": "技术总监",
		"pay": "50-100K",
		"address": "深圳 宝安区 福永",
		"year": "5-10年",
		"education": "本科",
		"companyName": "跨越速运",
		"tmt": "物流/仓储",
		"financing": "A轮",
		"peopleNum": "10000人以上",
		"img": "https://img2.bosszhipin.com/mcs/useravatar/20150401/9efebd3de653f939b85afa36b872f9428bee7c70fa2377c34db570f82ca84ea5_s.jpg",
		"recruiter": "柯小姐",
		"type": "招聘者"
	},
	{
		"jobName": "技术总监",
		"pay": "50-100K",
		"address": "深圳 宝安区 福永",
		"year": "5-10年",
		"education": "本科",
		"companyName": "跨越速运",
		"tmt": "物流/仓储",
		"financing": "A轮",
		"peopleNum": "10000人以上",
		"img": "https://img2.bosszhipin.com/mcs/useravatar/20150401/9efebd3de653f939b85afa36b872f9428bee7c70fa2377c34db570f82ca84ea5_s.jpg",
		"recruiter": "柯小姐",
		"type": "招聘者"
	},
	{
		"jobName": "技术总监",
		"pay": "50-100K",
		"address": "深圳 宝安区 福永",
		"year": "5-10年",
		"education": "本科",
		"companyName": "跨越速运",
		"tmt": "物流/仓储",
		"financing": "A轮",
		"peopleNum": "10000人以上",
		"img": "https://img2.bosszhipin.com/mcs/useravatar/20150401/9efebd3de653f939b85afa36b872f9428bee7c70fa2377c34db570f82ca84ea5_s.jpg",
		"recruiter": "柯小姐",
		"type": "招聘者"
	},
	{
		"jobName": "技术总监",
		"pay": "50-100K",
		"address": "深圳 宝安区 福永",
		"year": "5-10年",
		"education": "本科",
		"companyName": "跨越速运",
		"tmt": "物流/仓储",
		"financing": "A轮",
		"peopleNum": "10000人以上",
		"img": "https://img2.bosszhipin.com/mcs/useravatar/20150401/9efebd3de653f939b85afa36b872f9428bee7c70fa2377c34db570f82ca84ea5_s.jpg",
		"recruiter": "柯小姐",
		"type": "招聘者"
	},
	{
		"jobName": "技术总监",
		"pay": "50-100K",
		"address": "深圳 宝安区 福永",
		"year": "5-10年",
		"education": "本科",
		"companyName": "跨越速运",
		"tmt": "物流/仓储",
		"financing": "A轮",
		"peopleNum": "10000人以上",
		"img": "https://img2.bosszhipin.com/mcs/useravatar/20150401/9efebd3de653f939b85afa36b872f9428bee7c70fa2377c34db570f82ca84ea5_s.jpg",
		"recruiter": "柯小姐",
		"type": "招聘者"
	},
	{
		"jobName": "技术总监",
		"pay": "50-100K",
		"address": "深圳 宝安区 福永",
		"year": "5-10年",
		"education": "本科",
		"companyName": "跨越速运",
		"tmt": "物流/仓储",
		"financing": "A轮",
		"peopleNum": "10000人以上",
		"img": "https://img2.bosszhipin.com/mcs/useravatar/20150401/9efebd3de653f939b85afa36b872f9428bee7c70fa2377c34db570f82ca84ea5_s.jpg",
		"recruiter": "柯小姐",
		"type": "招聘者"
	},
	{
		"jobName": "技术总监",
		"pay": "50-100K",
		"address": "深圳 宝安区 福永",
		"year": "5-10年",
		"education": "本科",
		"companyName": "跨越速运",
		"tmt": "物流/仓储",
		"financing": "A轮",
		"peopleNum": "10000人以上",
		"img": "https://img2.bosszhipin.com/mcs/useravatar/20150401/9efebd3de653f939b85afa36b872f9428bee7c70fa2377c34db570f82ca84ea5_s.jpg",
		"recruiter": "柯小姐",
		"type": "招聘者"
	},
	{
		"jobName": "技术总监",
		"pay": "50-100K",
		"address": "深圳 宝安区 福永",
		"year": "5-10年",
		"education": "本科",
		"companyName": "跨越速运",
		"tmt": "物流/仓储",
		"financing": "A轮",
		"peopleNum": "10000人以上",
		"img": "https://img2.bosszhipin.com/mcs/useravatar/20150401/9efebd3de653f939b85afa36b872f9428bee7c70fa2377c34db570f82ca84ea5_s.jpg",
		"recruiter": "柯小姐",
		"type": "招聘者"
	},
	{
		"jobName": "技术总监",
		"pay": "50-100K",
		"address": "深圳 宝安区 福永",
		"year": "5-10年",
		"education": "本科",
		"companyName": "跨越速运",
		"tmt": "物流/仓储",
		"financing": "A轮",
		"peopleNum": "10000人以上",
		"img": "https://img2.bosszhipin.com/mcs/useravatar/20150401/9efebd3de653f939b85afa36b872f9428bee7c70fa2377c34db570f82ca84ea5_s.jpg",
		"recruiter": "柯小姐",
		"type": "招聘者"
	},
	{
		"jobName": "技术总监",
		"pay": "50-100K",
		"address": "深圳 宝安区 福永",
		"year": "5-10年",
		"education": "本科",
		"companyName": "跨越速运",
		"tmt": "物流/仓储",
		"financing": "A轮",
		"peopleNum": "10000人以上",
		"img": "https://img2.bosszhipin.com/mcs/useravatar/20150401/9efebd3de653f939b85afa36b872f9428bee7c70fa2377c34db570f82ca84ea5_s.jpg",
		"recruiter": "柯小姐",
		"type": "招聘者"
	},
	{
		"jobName": "技术总监",
		"pay": "50-100K",
		"address": "深圳 宝安区 福永",
		"year": "5-10年",
		"education": "本科",
		"companyName": "跨越速运",
		"tmt": "物流/仓储",
		"financing": "A轮",
		"peopleNum": "10000人以上",
		"img": "https://img2.bosszhipin.com/mcs/useravatar/20150401/9efebd3de653f939b85afa36b872f9428bee7c70fa2377c34db570f82ca84ea5_s.jpg",
		"recruiter": "柯小姐",
		"type": "招聘者"
	},
	{
		"jobName": "技术总监",
		"pay": "50-100K",
		"address": "深圳 宝安区 福永",
		"year": "5-10年",
		"education": "本科",
		"companyName": "跨越速运",
		"tmt": "物流/仓储",
		"financing": "A轮",
		"peopleNum": "10000人以上",
		"img": "https://img2.bosszhipin.com/mcs/useravatar/20150401/9efebd3de653f939b85afa36b872f9428bee7c70fa2377c34db570f82ca84ea5_s.jpg",
		"recruiter": "柯小姐",
		"type": "招聘者"
	}
]